{
  "chatMessage": [
    {
      "type": 0,
      "contentType": 1,
      "status": 2,
      "toId": "",
      "fromId": "1",
      "message": "122132",
      "createdBy": "1",
      "createdDate": 1540518777774,
      "id": "725943d7-6cef-44d0-8cae-4994434bdada",
      "fromName": "admin"
    },
    {
      "type": 0,
      "contentType": 1,
      "status": 2,
      "toId": "",
      "fromId": "b8c30ddc-ba75-447a-8634-13bd2e021781",
      "message": "21212",
      "createdBy": "b8c30ddc-ba75-447a-8634-13bd2e021781",
      "createdDate": 1540520092083,
      "id": "1d690300-4e2e-44f5-9b5e-c46cd7833d1a",
      "fromName": "12"
    },
    {
      "type": 0,
      "contentType": 1,
      "status": 2,
      "toId": "",
      "fromId": "1",
      "message": "1212",
      "createdBy": "1",
      "createdDate": 1540520100536,
      "id": "29fe581e-ac65-4341-b9d4-2b1709f3f3e3",
      "fromName": "admin"
    },
    {
      "type": 1,
      "contentType": 1,
      "status": 2,
      "toId": "1",
      "fromId": "b8c30ddc-ba75-447a-8634-13bd2e021781",
      "message": "12121",
      "createdBy": "b8c30ddc-ba75-447a-8634-13bd2e021781",
      "createdDate": 1540520147822,
      "id": "478c3168-e5ff-4783-a02d-4c34a6e48f6e",
      "fromName": "12"
    },
    {
      "type": 1,
      "contentType": 1,
      "status": 2,
      "toId": "b8c30ddc-ba75-447a-8634-13bd2e021781",
      "fromId": "1",
      "message": "1212",
      "createdBy": "1",
      "createdDate": 1540520158572,
      "id": "26d9e6d7-9952-4e0f-82c2-8ed0e62f73fc",
      "fromName": "admin"
    },
    {
      "type": 1,
      "contentType": 1,
      "status": 2,
      "toId": "b8c30ddc-ba75-447a-8634-13bd2e021781",
      "fromId": "1",
      "message": "12121",
      "createdBy": "1",
      "createdDate": 1540520166292,
      "id": "893772c0-ff44-4efa-8825-a5785fac8812",
      "fromName": "admin"
    },
    {
      "type": 1,
      "contentType": 1,
      "status": 2,
      "toId": "b8c30ddc-ba75-447a-8634-13bd2e021781",
      "fromId": "1",
      "message": "1111111111111",
      "createdBy": "1",
      "createdDate": 1540520170491,
      "id": "1ec83f59-5493-4428-b57e-af1a6446efa9",
      "fromName": "admin"
    },
    {
      "type": 1,
      "contentType": 1,
      "status": 2,
      "toId": "b8c30ddc-ba75-447a-8634-13bd2e021781",
      "fromId": "1",
      "message": "<p>dddddd</p>",
      "createdBy": "1",
      "createdDate": 1540520231605,
      "id": "f987ca07-c486-4a32-8da1-abe92c8d5655",
      "fromName": "admin"
    },
    {
      "type": 1,
      "contentType": 1,
      "status": 2,
      "toId": "b8c30ddc-ba75-447a-8634-13bd2e021781",
      "fromId": "1",
      "message": "<script>alert(1)</script>",
      "createdBy": "1",
      "createdDate": 1540520258795,
      "id": "9e11ff44-5bde-4eaa-beb7-268a6f2a6242",
      "fromName": "admin"
    },
    {
      "type": 0,
      "contentType": 1,
      "status": 2,
      "toId": "",
      "fromId": "b8c30ddc-ba75-447a-8634-13bd2e021781",
      "message": "1212",
      "createdBy": "b8c30ddc-ba75-447a-8634-13bd2e021781",
      "createdDate": 1540521962838,
      "id": "4abe1c16-613d-4981-a287-70160728da75",
      "fromName": "12"
    },
    {
      "type": 0,
      "contentType": 1,
      "status": 2,
      "toId": "",
      "fromId": "1",
      "message": "11111111111111111111111111",
      "createdBy": "1",
      "createdDate": 1540522506508,
      "id": "f784addc-288e-48eb-944b-62140c471d04",
      "fromName": "admin"
    },
    {
      "type": 2,
      "contentType": 1,
      "status": 2,
      "toId": "c20e4a1c-9fe3-4c1c-a133-cc2348edcdd6",
      "fromId": "1",
      "message": "44444444444444444444444444",
      "createdBy": "1",
      "createdDate": 1540522515348,
      "id": "89165bf1-a8f6-44b9-8741-326564d2dd59",
      "fromName": "admin"
    },
    {
      "type": 2,
      "contentType": 1,
      "status": 2,
      "toId": "b8fcbe93-9721-4771-aaec-8ca6a9c71085",
      "fromId": "1",
      "message": "5555555555555555",
      "createdBy": "1",
      "createdDate": 1540522548467,
      "id": "7a849e33-35ea-42a0-ae3b-1bd1ac1d011d"
    },
    {
      "type": 1,
      "contentType": 1,
      "status": 2,
      "toId": "1",
      "fromId": "b8c30ddc-ba75-447a-8634-13bd2e021781",
      "message": "121212",
      "createdBy": "b8c30ddc-ba75-447a-8634-13bd2e021781",
      "createdDate": 1540522567829,
      "id": "9ab22fa2-cc05-43b3-91e9-5a72d25cda79",
      "fromName": "12"
    },
    {
      "type": 1,
      "contentType": 1,
      "status": 1,
      "toId": "1",
      "fromId": "b8c30ddc-ba75-447a-8634-13bd2e021781",
      "message": "12121212",
      "createdBy": "b8c30ddc-ba75-447a-8634-13bd2e021781",
      "createdDate": 1540522582988,
      "id": "77d9f89f-bbf4-4680-8d29-ef190820c78a",
      "fromName": "12"
    },
    {
      "type": 1,
      "contentType": 1,
      "status": 1,
      "toId": "1",
      "fromId": "b8c30ddc-ba75-447a-8634-13bd2e021781",
      "message": "555555555555",
      "createdBy": "b8c30ddc-ba75-447a-8634-13bd2e021781",
      "createdDate": 1540522587308,
      "id": "de20666f-1d49-48f5-8592-c0487875ed7c",
      "fromName": "12"
    },
    {
      "type": 1,
      "contentType": 1,
      "status": 1,
      "toId": "1",
      "fromId": "b8c30ddc-ba75-447a-8634-13bd2e021781",
      "message": "看得见风科技的疯狂的九分裤",
      "createdBy": "b8c30ddc-ba75-447a-8634-13bd2e021781",
      "createdDate": 1540522613827,
      "id": "cd0f93cc-7ccf-478e-9c99-1aa88f164892",
      "fromName": "12"
    },
    {
      "type": 0,
      "contentType": 1,
      "status": 2,
      "toId": "",
      "fromId": "b8c30ddc-ba75-447a-8634-13bd2e021781",
      "message": "1212",
      "createdBy": "b8c30ddc-ba75-447a-8634-13bd2e021781",
      "createdDate": 1540524427307,
      "id": "249d9da2-9112-4db6-8319-9f73e4c9a0a5",
      "fromName": "12"
    },
    {
      "type": 0,
      "contentType": 1,
      "status": 2,
      "toId": "",
      "fromId": "b8c30ddc-ba75-447a-8634-13bd2e021781",
      "message": "1212",
      "createdBy": "b8c30ddc-ba75-447a-8634-13bd2e021781",
      "createdDate": 1540524429882,
      "id": "0f826866-ba63-457c-ac43-117cfd807d29",
      "fromName": "12"
    },
    {
      "type": 0,
      "contentType": 1,
      "status": 2,
      "toId": "",
      "fromId": "b8c30ddc-ba75-447a-8634-13bd2e021781",
      "message": "哈哈哈哈哈",
      "createdBy": "b8c30ddc-ba75-447a-8634-13bd2e021781",
      "createdDate": 1540524434599,
      "id": "60601fd6-2ec5-4f12-9467-8ee4b167d8be",
      "fromName": "12"
    },
    {
      "type": 0,
      "contentType": 1,
      "status": 2,
      "toId": "",
      "fromId": "b8c30ddc-ba75-447a-8634-13bd2e021781",
      "message": "1212",
      "createdBy": "b8c30ddc-ba75-447a-8634-13bd2e021781",
      "createdDate": 1540524481062,
      "id": "44a48032-83d3-4449-9505-edc623ff0aa3",
      "fromName": "12"
    },
    {
      "type": 2,
      "contentType": 1,
      "status": 2,
      "toId": "c20e4a1c-9fe3-4c1c-a133-cc2348edcdd6",
      "fromId": "b8c30ddc-ba75-447a-8634-13bd2e021781",
      "message": "121212",
      "createdBy": "b8c30ddc-ba75-447a-8634-13bd2e021781",
      "createdDate": 1540524570518,
      "id": "06f27f4d-050d-4e76-9793-b05238e8cd0d",
      "fromName": "12"
    },
    {
      "type": 0,
      "contentType": 1,
      "status": 2,
      "toId": "",
      "fromId": "1",
      "message": "1212121212",
      "createdBy": "1",
      "createdDate": 1540526319336,
      "id": "890e011e-7dc4-4362-9f3a-00bfec6d049a",
      "fromName": "admin"
    },
    {
      "type": 0,
      "contentType": 1,
      "status": 2,
      "toId": "",
      "fromId": "1",
      "message": "哈哈哈哈哈哈哈哈",
      "createdBy": "1",
      "createdDate": 1540526350399,
      "id": "f480b0af-c5e7-425d-ab86-265d0fe31b70",
      "fromName": "admin"
    },
    {
      "type": 0,
      "contentType": 1,
      "status": 2,
      "toId": "",
      "fromId": "1",
      "message": "121212",
      "createdBy": "1",
      "createdDate": 1540526366832,
      "id": "9aa7a533-0a07-47c8-bb8f-8cffbb643915",
      "fromName": "admin"
    },
    {
      "type": 2,
      "contentType": 1,
      "status": 2,
      "toId": "c20e4a1c-9fe3-4c1c-a133-cc2348edcdd6",
      "fromId": "1",
      "message": "111",
      "createdBy": "1",
      "createdDate": 1540526494497,
      "id": "1caf1473-2099-4e55-9182-3e98af15d09d",
      "fromName": "admin"
    },
    {
      "type": 0,
      "contentType": 1,
      "status": 2,
      "toId": "",
      "fromId": "1",
      "message": "1",
      "createdBy": "1",
      "createdDate": 1540526588238,
      "id": "92005446-44f7-4fd4-a97d-eab9bf6faa73",
      "fromName": "admin"
    },
    {
      "type": 0,
      "contentType": 1,
      "status": 2,
      "toId": "",
      "fromId": "b8c30ddc-ba75-447a-8634-13bd2e021781",
      "message": "2",
      "createdBy": "b8c30ddc-ba75-447a-8634-13bd2e021781",
      "createdDate": 1540526608271,
      "id": "f9aa89a0-7312-4774-aeaf-765f4e5993b9",
      "fromName": "12"
    },
    {
      "type": 2,
      "contentType": 1,
      "status": 2,
      "toId": "c20e4a1c-9fe3-4c1c-a133-cc2348edcdd6",
      "fromId": "b8c30ddc-ba75-447a-8634-13bd2e021781",
      "message": "3",
      "createdBy": "b8c30ddc-ba75-447a-8634-13bd2e021781",
      "createdDate": 1540526625359,
      "id": "241da5df-1bb2-4abd-aae2-13670c3df77a",
      "fromName": "12"
    },
    {
      "type": 2,
      "contentType": 1,
      "status": 2,
      "toId": "c20e4a1c-9fe3-4c1c-a133-cc2348edcdd6",
      "fromId": "b8c30ddc-ba75-447a-8634-13bd2e021781",
      "message": "121212",
      "createdBy": "b8c30ddc-ba75-447a-8634-13bd2e021781",
      "createdDate": 1540527271466,
      "id": "5f6e22fc-c34b-4d5f-aaa6-90fb1e62eb7e",
      "fromName": "12"
    },
    {
      "type": 0,
      "contentType": 1,
      "status": 2,
      "toId": "",
      "fromId": "1",
      "message": "gggggggggggggggggg",
      "createdBy": "1",
      "createdDate": 1540527282201,
      "id": "c6f31027-71eb-4c36-b2a0-072dcd846707",
      "fromName": "admin"
    },
    {
      "type": 0,
      "contentType": 1,
      "status": 2,
      "toId": "",
      "fromId": "1",
      "message": "11111111111111",
      "createdBy": "1",
      "createdDate": 1540527319616,
      "id": "73897a1d-0420-409e-b469-446ff29aed95",
      "fromName": "admin"
    },
    {
      "type": 0,
      "contentType": 1,
      "status": 2,
      "toId": "",
      "fromId": "b8c30ddc-ba75-447a-8634-13bd2e021781",
      "message": "1",
      "createdBy": "b8c30ddc-ba75-447a-8634-13bd2e021781",
      "createdDate": 1540527386961,
      "id": "c6e2f659-951d-44a5-a288-a32eba45f8a0",
      "fromName": "12"
    },
    {
      "type": 2,
      "contentType": 1,
      "status": 2,
      "toId": "c20e4a1c-9fe3-4c1c-a133-cc2348edcdd6",
      "fromId": "b8c30ddc-ba75-447a-8634-13bd2e021781",
      "message": "121212",
      "createdBy": "b8c30ddc-ba75-447a-8634-13bd2e021781",
      "createdDate": 1540527411145,
      "id": "9dba07a0-f5d6-41ad-96e6-fa2f3895d899",
      "fromName": "12"
    },
    {
      "type": 2,
      "contentType": 1,
      "status": 2,
      "toId": "c20e4a1c-9fe3-4c1c-a133-cc2348edcdd6",
      "fromId": "b8c30ddc-ba75-447a-8634-13bd2e021781",
      "message": "121212",
      "createdBy": "b8c30ddc-ba75-447a-8634-13bd2e021781",
      "createdDate": 1540527430947,
      "id": "63bc8f58-e2c2-43e2-8eb6-f71ece202f9a",
      "fromName": "12"
    },
    {
      "type": 2,
      "contentType": 1,
      "status": 2,
      "toId": "c20e4a1c-9fe3-4c1c-a133-cc2348edcdd6",
      "fromId": "b8c30ddc-ba75-447a-8634-13bd2e021781",
      "message": "1212",
      "createdBy": "b8c30ddc-ba75-447a-8634-13bd2e021781",
      "createdDate": 1540527435401,
      "id": "52575881-7dac-4222-887c-a6e98d3a64d1",
      "fromName": "12"
    },
    {
      "type": 0,
      "contentType": 1,
      "status": 2,
      "toId": "",
      "fromId": "b8c30ddc-ba75-447a-8634-13bd2e021781",
      "message": "45",
      "createdBy": "b8c30ddc-ba75-447a-8634-13bd2e021781",
      "createdDate": 1540527495209,
      "id": "3051d033-b09c-4091-b06a-8a32813e4490",
      "fromName": "12"
    },
    {
      "type": 2,
      "contentType": 1,
      "status": 2,
      "toId": "2eae2d41-d8ab-4e7a-bad5-ccb657b06dc9",
      "fromId": "b8c30ddc-ba75-447a-8634-13bd2e021781",
      "message": "1212",
      "createdBy": "b8c30ddc-ba75-447a-8634-13bd2e021781",
      "createdDate": 1540527511977,
      "id": "c286fb51-6b12-4bab-9c11-94f63cb3fdba",
      "fromName": "12"
    },
    {
      "type": 2,
      "contentType": 1,
      "status": 2,
      "toId": "2eae2d41-d8ab-4e7a-bad5-ccb657b06dc9",
      "fromId": "1",
      "message": "121212",
      "createdBy": "1",
      "createdDate": 1540527524174,
      "id": "03f199bb-54b2-4db7-8a23-90262fe8b67f",
      "fromName": "admin"
    },
    {
      "type": 2,
      "contentType": 1,
      "status": 2,
      "toId": "2eae2d41-d8ab-4e7a-bad5-ccb657b06dc9",
      "fromId": "b8c30ddc-ba75-447a-8634-13bd2e021781",
      "message": "1212",
      "createdBy": "b8c30ddc-ba75-447a-8634-13bd2e021781",
      "createdDate": 1540527533368,
      "id": "a82db73a-4e95-472f-adb0-78b311394d12",
      "fromName": "12"
    },
    {
      "type": 0,
      "contentType": 1,
      "status": 2,
      "toId": "",
      "fromId": "1",
      "message": "88888888888888",
      "createdBy": "1",
      "createdDate": 1540527597407,
      "id": "28e004cb-a91e-46f3-ad62-71dbbc8f23fe",
      "fromName": "admin"
    },
    {
      "type": 0,
      "contentType": 1,
      "status": 2,
      "toId": "",
      "fromId": "1",
      "message": "999999999999",
      "createdBy": "1",
      "createdDate": 1540527626479,
      "id": "54243a7e-05ac-40ee-9b41-80e820ce913a",
      "fromName": "admin"
    },
    {
      "type": 0,
      "contentType": 1,
      "status": 2,
      "toId": "",
      "fromId": "b8c30ddc-ba75-447a-8634-13bd2e021781",
      "message": "6666",
      "createdBy": "b8c30ddc-ba75-447a-8634-13bd2e021781",
      "createdDate": 1540527759260,
      "id": "3b88cab4-3cdd-4310-8cb7-80e9da811d18",
      "fromName": "12"
    },
    {
      "type": 2,
      "contentType": 1,
      "status": 2,
      "toId": "c20e4a1c-9fe3-4c1c-a133-cc2348edcdd6",
      "fromId": "1",
      "message": "121212",
      "createdBy": "1",
      "createdDate": 1540527769193,
      "id": "27dc3a0c-90df-404e-8b8f-133526ea9662",
      "fromName": "admin"
    },
    {
      "type": 2,
      "contentType": 1,
      "status": 2,
      "toId": "c20e4a1c-9fe3-4c1c-a133-cc2348edcdd6",
      "fromId": "b8c30ddc-ba75-447a-8634-13bd2e021781",
      "message": "1212",
      "createdBy": "b8c30ddc-ba75-447a-8634-13bd2e021781",
      "createdDate": 1540527792573,
      "id": "9c8ea595-0df9-4a2a-af86-a0b5148653e2",
      "fromName": "12"
    },
    {
      "type": 0,
      "contentType": 1,
      "status": 2,
      "toId": "",
      "fromId": "1",
      "message": "000000000000000",
      "createdBy": "1",
      "createdDate": 1540527814959,
      "id": "8901f4a8-e80f-4496-abc0-73b0e2e4ccf7",
      "fromName": "admin"
    },
    {
      "type": 0,
      "contentType": 1,
      "status": 2,
      "toId": "",
      "fromId": "1",
      "message": "1212",
      "createdBy": "1",
      "createdDate": 1540536638486,
      "id": "494f1f42-e541-43cd-bcba-ef7e20892525",
      "fromName": "admin"
    },
    {
      "type": 0,
      "contentType": 1,
      "status": 2,
      "toId": "",
      "fromId": "1",
      "message": "1212",
      "createdBy": "1",
      "createdDate": 1540536641076,
      "id": "4314c561-9144-4fb8-9e48-78533b4c89f6",
      "fromName": "admin"
    },
    {
      "type": 0,
      "contentType": 1,
      "status": 2,
      "toId": "",
      "fromId": "1",
      "message": "1212",
      "createdBy": "1",
      "createdDate": 1540536643157,
      "id": "774fa2f7-50f5-4976-85f3-03ae2a2fd315",
      "fromName": "admin"
    },
    {
      "type": 0,
      "contentType": 1,
      "status": 2,
      "toId": "",
      "fromId": "1",
      "message": "121212",
      "createdBy": "1",
      "createdDate": 1540536645043,
      "id": "106e8015-a996-4749-825d-1579ed569445",
      "fromName": "admin"
    },
    {
      "type": 0,
      "contentType": 1,
      "status": 2,
      "toId": "",
      "fromId": "1",
      "message": "121212",
      "createdBy": "1",
      "createdDate": 1540536646731,
      "id": "9ec7e605-3634-4e35-b7af-f220c0782a46",
      "fromName": "admin"
    },
    {
      "type": 0,
      "contentType": 1,
      "status": 2,
      "toId": "",
      "fromId": "1",
      "message": "99999",
      "createdBy": "1",
      "createdDate": 1540536674740,
      "id": "6f3a214e-4f32-4db5-ada4-9a84d22fcfd0",
      "fromName": "admin"
    },
    {
      "type": 0,
      "contentType": 1,
      "status": 2,
      "toId": "",
      "fromId": "1",
      "message": "565656",
      "createdBy": "1",
      "createdDate": 1540536683484,
      "id": "64ee148d-f7fa-44a2-8c72-f6b41f2caf4e",
      "fromName": "admin"
    },
    {
      "type": 0,
      "contentType": 1,
      "status": 2,
      "toId": "",
      "fromId": "1",
      "message": "5656",
      "createdBy": "1",
      "createdDate": 1540536685583,
      "id": "ad1bead9-e65b-4f02-88cd-4f2333076886",
      "fromName": "admin"
    },
    {
      "type": 0,
      "contentType": 1,
      "status": 2,
      "toId": "",
      "fromId": "1",
      "message": "565656",
      "createdBy": "1",
      "createdDate": 1540536686939,
      "id": "968a9d06-2f52-4d92-b9e8-2ac4df411cb1",
      "fromName": "admin"
    },
    {
      "type": 0,
      "contentType": 1,
      "status": 2,
      "toId": "",
      "fromId": "1",
      "message": "121212",
      "createdBy": "1",
      "createdDate": 1540537293647,
      "id": "79191cc0-6549-43eb-890d-f8ea18fa5204",
      "fromName": "admin"
    },
    {
      "type": 0,
      "contentType": 1,
      "status": 2,
      "toId": "",
      "fromId": "1",
      "message": "1212",
      "createdBy": "1",
      "createdDate": 1540537297375,
      "id": "84fa3ddb-4de3-4b2c-8cf2-67f136fe2ed0",
      "fromName": "admin"
    },
    {
      "type": 0,
      "contentType": 1,
      "status": 2,
      "toId": "",
      "fromId": "1",
      "message": "1212",
      "createdBy": "1",
      "createdDate": 1540537301551,
      "id": "8ca776ad-67c5-4cfe-af48-d87515496e54",
      "fromName": "admin"
    },
    {
      "type": 0,
      "contentType": 1,
      "status": 2,
      "toId": "",
      "fromId": "1",
      "message": "1212",
      "createdBy": "1",
      "createdDate": 1540537305215,
      "id": "a1c0ae6a-36d0-45ac-950d-d1b64e864544",
      "fromName": "admin"
    },
    {
      "type": 0,
      "contentType": 1,
      "status": 2,
      "toId": "",
      "fromId": "1",
      "message": "121212",
      "createdBy": "1",
      "createdDate": 1540537324703,
      "id": "86a96843-7b4d-4bd6-9797-246e7fe59416",
      "fromName": "admin"
    },
    {
      "type": 0,
      "contentType": 1,
      "status": 2,
      "toId": "",
      "fromId": "1",
      "message": "1212",
      "createdBy": "1",
      "createdDate": 1540537330374,
      "id": "f6e3cee8-811d-48b9-b541-7f99d24e6e77",
      "fromName": "admin"
    },
    {
      "type": 0,
      "contentType": 1,
      "status": 2,
      "toId": "",
      "fromId": "1",
      "message": "1212",
      "createdBy": "1",
      "createdDate": 1540537440254,
      "id": "d7649cdf-b32c-49ef-ba2a-cfdc5671c070",
      "fromName": "admin"
    },
    {
      "type": 0,
      "contentType": 1,
      "status": 2,
      "toId": "",
      "fromId": "1",
      "message": "1212",
      "createdBy": "1",
      "createdDate": 1540537444184,
      "id": "2365a935-945e-4c41-93b7-164a91526074",
      "fromName": "admin"
    },
    {
      "type": 0,
      "contentType": 1,
      "status": 2,
      "toId": "",
      "fromId": "1",
      "message": "1212",
      "createdBy": "1",
      "createdDate": 1540537447118,
      "id": "4fafecfe-7377-455a-9fb7-688c701819d4",
      "fromName": "admin"
    },
    {
      "type": 0,
      "contentType": 1,
      "status": 2,
      "toId": "",
      "fromId": "1",
      "message": "1212",
      "createdBy": "1",
      "createdDate": 1540537452399,
      "id": "c326970b-461a-4ac5-80a8-5d1b0ee5fabb",
      "fromName": "admin"
    },
    {
      "type": 0,
      "contentType": 1,
      "status": 2,
      "toId": "",
      "fromId": "1",
      "message": "121212",
      "createdBy": "1",
      "createdDate": 1540537653579,
      "id": "c4ae1578-45c6-4184-aea6-6d0103e8a18c",
      "fromName": "admin"
    },
    {
      "type": 0,
      "contentType": 1,
      "status": 2,
      "toId": "",
      "fromId": "1",
      "message": "1212",
      "createdBy": "1",
      "createdDate": 1540537658020,
      "id": "a382c108-630f-459c-ac62-364865e54825",
      "fromName": "admin"
    },
    {
      "type": 0,
      "contentType": 1,
      "status": 2,
      "toId": "",
      "fromId": "1",
      "message": "1212",
      "createdBy": "1",
      "createdDate": 1540537661340,
      "id": "6e1ae04c-f6db-4c7b-9f33-f776ddca9a04",
      "fromName": "admin"
    },
    {
      "type": 0,
      "contentType": 1,
      "status": 2,
      "toId": "",
      "fromId": "1",
      "message": "1212",
      "createdBy": "1",
      "createdDate": 1540537663894,
      "id": "73743b8b-a473-4851-9e69-db680fd5ca02",
      "fromName": "admin"
    },
    {
      "type": 0,
      "contentType": 1,
      "status": 2,
      "toId": "",
      "fromId": "1",
      "message": "1212",
      "createdBy": "1",
      "createdDate": 1540537741548,
      "id": "e742c9c1-5321-41b7-a9fc-0e08de2fd49e",
      "fromName": "admin"
    },
    {
      "type": 0,
      "contentType": 1,
      "status": 2,
      "toId": "",
      "fromId": "1",
      "message": "1212",
      "createdBy": "1",
      "createdDate": 1540537744076,
      "id": "833de566-4f8a-4a9b-b6d5-b9af88985088",
      "fromName": "admin"
    },
    {
      "type": 0,
      "contentType": 1,
      "status": 2,
      "toId": "",
      "fromId": "1",
      "message": "1212",
      "createdBy": "1",
      "createdDate": 1540537810579,
      "id": "78b8a277-0b95-421d-9829-91cb5a8ab458",
      "fromName": "admin"
    },
    {
      "type": 0,
      "contentType": 1,
      "status": 2,
      "toId": "",
      "fromId": "1",
      "message": "121212",
      "createdBy": "1",
      "createdDate": 1540537815459,
      "id": "fd9c2bb4-4eac-4410-895d-b35c2069829e",
      "fromName": "admin"
    },
    {
      "type": 0,
      "contentType": 1,
      "status": 2,
      "toId": "",
      "fromId": "1",
      "message": "121212",
      "createdBy": "1",
      "createdDate": 1540537821355,
      "id": "01c42716-c854-4aef-a9ee-3be8f9061eb3",
      "fromName": "admin"
    },
    {
      "type": 0,
      "contentType": 1,
      "status": 2,
      "toId": "",
      "fromId": "1",
      "message": "1212",
      "createdBy": "1",
      "createdDate": 1540537823444,
      "id": "93d70c9b-bb5e-496e-8ef4-23657cf211a3"
    },
    {
      "type": 2,
      "contentType": 1,
      "status": 2,
      "toId": "77f264e8-d8bb-486a-9a35-42eaeb7d4262",
      "fromId": "1",
      "message": "121212",
      "createdBy": "1",
      "createdDate": 1540538392444,
      "id": "032c5945-70e9-46c8-9182-0189077fac2c",
      "fromName": "admin"
    },
    {
      "type": 2,
      "contentType": 1,
      "status": 2,
      "toId": "41fe5843-5316-4381-b885-4bf688a25b36",
      "fromId": "1",
      "message": "232323",
      "createdBy": "1",
      "createdDate": 1540538443962,
      "id": "cea58c6e-8d05-484c-9a96-34d2c1bb0ca2",
      "fromName": "admin"
    },
    {
      "type": 1,
      "contentType": 1,
      "status": 2,
      "toId": "b8c30ddc-ba75-447a-8634-13bd2e021781",
      "fromId": "1",
      "message": "121212",
      "createdBy": "1",
      "createdDate": 1540539047027,
      "id": "1602db1a-35fc-4745-aa07-c0f3c2fd9055",
      "fromName": "admin"
    },
    {
      "type": 1,
      "contentType": 1,
      "status": 2,
      "toId": "b8c30ddc-ba75-447a-8634-13bd2e021781",
      "fromId": "1",
      "message": "食疗",
      "createdBy": "1",
      "createdDate": 1540539056162,
      "id": "2c4fbc13-a81a-4d59-8e17-ceca1746b331",
      "fromName": "admin"
    },
    {
      "type": 1,
      "contentType": 1,
      "status": 2,
      "toId": "b8c30ddc-ba75-447a-8634-13bd2e021781",
      "fromId": "1",
      "message": "1",
      "createdBy": "1",
      "createdDate": 1540539412910,
      "id": "f337e45c-68e4-4eb9-ba7e-29704c22833d",
      "fromName": "admin"
    },
    {
      "type": 1,
      "contentType": 1,
      "status": 2,
      "toId": "1",
      "fromId": "b8c30ddc-ba75-447a-8634-13bd2e021781",
      "message": "2",
      "createdBy": "b8c30ddc-ba75-447a-8634-13bd2e021781",
      "createdDate": 1540539417977,
      "id": "dc1f2f98-b14d-469c-bf60-270531ca2f59",
      "fromName": "12"
    },
    {
      "type": 1,
      "contentType": 1,
      "status": 2,
      "toId": "b8c30ddc-ba75-447a-8634-13bd2e021781",
      "fromId": "1",
      "message": "3",
      "createdBy": "1",
      "createdDate": 1540539426735,
      "id": "24d029c0-c7dc-41a1-8dcf-6a4722494ffd",
      "fromName": "admin"
    },
    {
      "type": 1,
      "contentType": 1,
      "status": 2,
      "toId": "1",
      "fromId": "b8c30ddc-ba75-447a-8634-13bd2e021781",
      "message": "4",
      "createdBy": "b8c30ddc-ba75-447a-8634-13bd2e021781",
      "createdDate": 1540539432216,
      "id": "29e1cf42-7047-4c8d-8573-8b04ce49c392",
      "fromName": "12"
    },
    {
      "type": 0,
      "contentType": 1,
      "status": 2,
      "toId": "",
      "fromId": "1",
      "message": "1212",
      "createdBy": "1",
      "createdDate": 1540540213091,
      "id": "f927704d-0d03-4b28-ac6d-09292061b6f3"
    },
    {
      "type": 1,
      "contentType": 1,
      "status": 2,
      "toId": "b8c30ddc-ba75-447a-8634-13bd2e021781",
      "fromId": "1",
      "message": "2323",
      "createdBy": "1",
      "createdDate": 1540540252041,
      "id": "0d9ba7a7-5552-4452-ab06-21ae93de89ed",
      "fromName": "admin"
    },
    {
      "type": 2,
      "contentType": 1,
      "status": 2,
      "toId": "2eae2d41-d8ab-4e7a-bad5-ccb657b06dc9",
      "fromId": "1",
      "message": "1212",
      "createdBy": "1",
      "createdDate": 1540540815115,
      "id": "f757651b-a934-42ca-8e29-aafa03003f12",
      "fromName": "admin"
    },
    {
      "type": 0,
      "contentType": 1,
      "status": 2,
      "toId": "",
      "fromId": "1",
      "message": "1212",
      "createdBy": "1",
      "createdDate": 1540540914412,
      "id": "ab554485-cd08-4a7f-9d85-8c26759b8401"
    },
    {
      "type": 2,
      "contentType": 1,
      "status": 2,
      "toId": "2eae2d41-d8ab-4e7a-bad5-ccb657b06dc9",
      "fromId": "1",
      "message": "1212",
      "createdBy": "1",
      "createdDate": 1540541988271,
      "id": "e2250fb6-7d6a-4b40-af01-ba17639e5597"
    },
    {
      "type": 2,
      "contentType": 1,
      "status": 2,
      "toId": "2eae2d41-d8ab-4e7a-bad5-ccb657b06dc9",
      "fromId": "1",
      "message": "1212",
      "createdBy": "1",
      "createdDate": 1540541992021,
      "id": "a7434f07-4345-4e37-b622-f458b71c99df"
    },
    {
      "type": 0,
      "contentType": 1,
      "status": 2,
      "toId": "",
      "fromId": "1",
      "message": "dfdf",
      "createdBy": "1",
      "createdDate": 1540542012357,
      "id": "5a35854a-af4f-4324-b117-564ceb6161c0"
    },
    {
      "type": 0,
      "contentType": 1,
      "status": 2,
      "toId": "",
      "fromId": "1",
      "message": "ttt",
      "createdBy": "1",
      "createdDate": 1540542024469,
      "id": "1c97a7c9-0643-4f62-b680-3d34fe31e42a"
    },
    {
      "type": 0,
      "contentType": 1,
      "status": 2,
      "toId": "",
      "fromId": "1",
      "message": "yyy",
      "createdBy": "1",
      "createdDate": 1540542144236,
      "id": "1b0f1d67-95b2-4bf5-b4fe-35724111f3d7"
    },
    {
      "type": 1,
      "contentType": 1,
      "status": 2,
      "toId": "b8c30ddc-ba75-447a-8634-13bd2e021781",
      "fromId": "1",
      "message": "ttt",
      "createdBy": "1",
      "createdDate": 1540542158436,
      "id": "83fc10b1-6a37-441c-afb0-e7735154f335"
    },
    {
      "type": 2,
      "contentType": 1,
      "status": 2,
      "toId": "c20e4a1c-9fe3-4c1c-a133-cc2348edcdd6",
      "fromId": "1",
      "message": "yuyuyu",
      "createdBy": "1",
      "createdDate": 1540542167428,
      "id": "550380d3-32d3-46f9-841b-9088161218f6"
    },
    {
      "type": 0,
      "contentType": 1,
      "status": 2,
      "toId": "",
      "fromId": "1",
      "message": "o",
      "createdBy": "1",
      "createdDate": 1540545311164,
      "id": "55ebfb56-5017-4b2a-9adb-de6c71d5e1b1"
    },
    {
      "type": 0,
      "contentType": 1,
      "status": 2,
      "toId": "",
      "fromId": "1",
      "message": "000000",
      "createdBy": "1",
      "createdDate": 1540545343949,
      "id": "101af49f-7477-462a-a8d4-49a3601057de"
    }
  ]
}